boron/__init__.py
boron/builder.py
boron/c_lib.dll
boron/cli.py
boron/docgen.py
boron/lineage.py
boron/testbench.py
src/__init__.py
src/py/__init__.py
src/py/greet.py
boron_v1-0.1.2.dist-info/LICENSE
boron_v1-0.1.2.dist-info/METADATA
boron_v1-0.1.2.dist-info/WHEEL
boron_v1-0.1.2.dist-info/entry_points.txt
boron_v1-0.1.2.dist-info/top_level.txt
boron_v1-0.1.2.dist-info/RECORD
