Metadata-Version: 2.1
Name: boron-v1
Version: 0.1.2
Summary: Link programming languages effortlessly using Boron (.bn) files.
Author: Harsith S
Author-email: boron.version.1@gmail.com
License: MIT
Classifier: Programming Language :: Python :: 3
Classifier: Operating System :: OS Independent
Classifier: License :: OSI Approved :: MIT License
Requires-Python: >=3.6
License-File: LICENSE
